[
    {
        "name": "Ben",
        "performances": [
            {
                "id": "Asian American Student Conference",
                "name": "Asian American Student Conference",
                "type": "School Event",
                "date": "February 28th, 2026",
                "day": "Saturday",
                "start": "7:30 PM - 9:00 PM (TBD)",
                "arrive": "TBD",
                "location": "Duke University (TBD)",
                "availability": "Busy"
            },
            {
                "id": "Jecin Wedding Performance",
                "name": "Jecin Wedding Performance",
                "type": "Wedding",
                "date": "April, 2026 (TBD)",
                "day": "TBD",
                "start": "TBD",
                "arrive": "TBD",
                "location": "TBD",
                "availability": "Maybe"
            }
        ]
    },
    {
        "name": "kiki",
        "performances": [
            {
                "id": "Asian American Student Conference",
                "name": "Asian American Student Conference",
                "type": "School Event",
                "date": "February 28th, 2026",
                "day": "Saturday",
                "start": "7:30 PM - 9:00 PM (TBD)",
                "arrive": "TBD",
                "location": "Gross Hall, Duke University",
                "availability": "Maybe",
                "extra": "Room 107?"
            },
            {
                "id": "Jecin Wedding Performance",
                "name": "Jecin Wedding Performance",
                "type": "Wedding",
                "date": "April 26th, 2026",
                "day": "Sunday",
                "start": "9:45 PM",
                "arrive": "9:15 PM",
                "location": "6304 Old Henks Rd, Apex NC",
                "availability": "Free"
            }
        ]
    },
    {
        "name": "Jayden Ly",
        "performances": [
            {
                "id": "Asian American Student Conference",
                "name": "Asian American Student Conference",
                "type": "School Event",
                "date": "February 28th, 2026",
                "day": "Saturday",
                "start": "7:30 PM - 9:00 PM (TBD)",
                "arrive": "TBD",
                "location": "Duke University (TBD)",
                "availability": "Free"
            },
            {
                "id": "Jecin Wedding Performance",
                "name": "Jecin Wedding Performance",
                "type": "Wedding",
                "date": "April, 2026 (TBD)",
                "day": "TBD",
                "start": "TBD",
                "arrive": "TBD",
                "location": "TBD",
                "availability": "Maybe"
            }
        ]
    },
    {
        "name": "Quynh V",
        "performances": [
            {
                "id": "Asian American Student Conference",
                "name": "Asian American Student Conference",
                "type": "School Event",
                "date": "February 28th, 2026",
                "day": "Saturday",
                "start": "7:30 PM - 9:00 PM (TBD)",
                "arrive": "TBD",
                "location": "Duke University (TBD)",
                "availability": "Free"
            },
            {
                "id": "Jecin Wedding Performance",
                "name": "Jecin Wedding Performance",
                "type": "Wedding",
                "date": "April, 2026 (TBD)",
                "day": "TBD",
                "start": "TBD",
                "arrive": "TBD",
                "location": "TBD",
                "availability": "Maybe"
            }
        ]
    },
    {
        "name": "John Pham",
        "performances": [
            {
                "id": "Asian American Student Conference",
                "name": "Asian American Student Conference",
                "type": "School Event",
                "date": "February 28th, 2026",
                "day": "Saturday",
                "start": "7:30 PM - 9:00 PM (TBD)",
                "arrive": "TBD",
                "location": "Duke University (TBD)",
                "availability": "Free"
            },
            {
                "id": "Jecin Wedding Performance",
                "name": "Jecin Wedding Performance",
                "type": "Wedding",
                "date": "April, 2026 (TBD)",
                "day": "TBD",
                "start": "TBD",
                "arrive": "TBD",
                "location": "TBD",
                "availability": "Free"
            }
        ]
    },
    {
        "name": "Connery",
        "performances": [
            {
                "id": "Asian American Student Conference",
                "name": "Asian American Student Conference",
                "type": "School Event",
                "date": "February 28th, 2026",
                "day": "Saturday",
                "start": "7:30 PM - 9:00 PM (TBD)",
                "arrive": "TBD",
                "location": "Gross Hall, Duke University",
                "availability": "Busy",
                "extra": "Room 107?"
            },
            {
                "id": "Jecin Wedding Performance",
                "name": "Jecin Wedding Performance",
                "type": "Wedding",
                "date": "April 26th, 2026",
                "day": "Sunday",
                "start": "9:45 PM",
                "arrive": "9:15 PM",
                "location": "6304 Old Henks Rd, Apex NC",
                "availability": "Free"
            }
        ]
    },
    {
        "name": "steven",
        "performances": [
            {
                "id": "Asian American Student Conference",
                "name": "Asian American Student Conference",
                "type": "School Event",
                "date": "February 28th, 2026",
                "day": "Saturday",
                "start": "7:30 PM - 9:00 PM (TBD)",
                "arrive": "TBD",
                "location": "Gross Hall, Duke University",
                "availability": "Maybe",
                "extra": "Room 107?"
            },
            {
                "id": "Jecin Wedding Performance",
                "name": "Jecin Wedding Performance",
                "type": "Wedding",
                "date": "April 26th, 2026",
                "day": "Sunday",
                "start": "9:45 PM",
                "arrive": "9:15 PM",
                "location": "6304 Old Henks Rd, Apex NC",
                "availability": "Free"
            }
        ]
    },
    {
        "name": "Vy",
        "performances": [
            {
                "id": "Asian American Student Conference",
                "name": "Asian American Student Conference",
                "type": "School Event",
                "date": "February 28th, 2026",
                "day": "Saturday",
                "start": "7:30 PM - 9:00 PM (TBD)",
                "arrive": "TBD",
                "location": "Gross Hall, Duke University",
                "availability": "Free",
                "extra": "Room 107?"
            },
            {
                "id": "Jecin Wedding Performance",
                "name": "Jecin Wedding Performance",
                "type": "Wedding",
                "date": "April 26th, 2026",
                "day": "Sunday",
                "start": "9:45 PM",
                "arrive": "9:15 PM",
                "location": "6304 Old Henks Rd, Apex NC",
                "availability": "Free"
            }
        ]
    },
    {
        "name": "John Le",
        "performances": [
            {
                "id": "Asian American Student Conference",
                "name": "Asian American Student Conference",
                "type": "School Event",
                "date": "February 28th, 2026",
                "day": "Saturday",
                "start": "7:30 PM - 9:00 PM (TBD)",
                "arrive": "TBD",
                "location": "Gross Hall, Duke University",
                "availability": "Busy",
                "extra": "Room 107?"
            },
            {
                "id": "Jecin Wedding Performance",
                "name": "Jecin Wedding Performance",
                "type": "Wedding",
                "date": "April 26th, 2026",
                "day": "Sunday",
                "start": "9:45 PM",
                "arrive": "9:15 PM",
                "location": "6304 Old Henks Rd, Apex NC",
                "availability": "Maybe"
            }
        ]
    },
    {
        "name": "Jason",
        "performances": [
            {
                "id": "Asian American Student Conference",
                "name": "Asian American Student Conference",
                "type": "School Event",
                "date": "February 28th, 2026",
                "day": "Saturday",
                "start": "7:30 PM - 9:00 PM (TBD)",
                "arrive": "TBD",
                "location": "Gross Hall, Duke University",
                "availability": "Free",
                "extra": "Room 107?"
            },
            {
                "id": "Jecin Wedding Performance",
                "name": "Jecin Wedding Performance",
                "type": "Wedding",
                "date": "April 26th, 2026",
                "day": "Sunday",
                "start": "9:45 PM",
                "arrive": "9:15 PM",
                "location": "6304 Old Henks Rd, Apex NC",
                "availability": "Free"
            }
        ]
    }
]